pipy_test_xiaoqiang/__init__.py
pipy_test_xiaoqiang/cli.py
pipy_test_xiaoqiang/main.py
pipy_test_xiaoqiang-1.1.2.dist-info/METADATA
pipy_test_xiaoqiang-1.1.2.dist-info/WHEEL
pipy_test_xiaoqiang-1.1.2.dist-info/entry_points.txt
pipy_test_xiaoqiang-1.1.2.dist-info/top_level.txt
pipy_test_xiaoqiang-1.1.2.dist-info/RECORD
